xaal/__init__.py
xaal/fauxmo/__init__.py
xaal/fauxmo/__main__.py
xaal/fauxmo/binding.py
xaal/fauxmo/gw.py
xaal_fauxmo-0.2.3.dist-info/METADATA
xaal_fauxmo-0.2.3.dist-info/WHEEL
xaal_fauxmo-0.2.3.dist-info/top_level.txt
xaal_fauxmo-0.2.3.dist-info/RECORD
