Metadata-Version: 2.4
Name: xaal.fauxmo
Version: 0.2.3
Summary: xAAL to Wemo fake emulations
Author-email: Jerome Kerdreux <Jerome.Kerdreux@imt-atlantique.fr>
License-Expression: GPL-3.0-or-later
Project-URL: Homepage, https://recherche.imt-atlantique.fr/xaal/
Project-URL: Documentation, https://gitlab.imt-atlantique.fr/xaal/code/python/-/blob/main/devices/emulations/Fauxmo/README.rst
Project-URL: Source, https://gitlab.imt-atlantique.fr/xaal/code/python/-/tree/main/devices/emulations/Fauxmo
Keywords: xaal,wemo,alexa
Classifier: Programming Language :: Python
Classifier: Topic :: Home Automation
Requires-Dist: xaal.lib
Requires-Dist: fauxmo==0.6
Requires-Dist: nest_asyncio
